azure_utils/__init__.py
azure_utils/blob_storage.py
azure_utils/utils/__init__.py
azure_utils/utils/blob_storage_utils.py
azure_utils-0.4.0.dist-info/LICENSE
azure_utils-0.4.0.dist-info/METADATA
azure_utils-0.4.0.dist-info/WHEEL
azure_utils-0.4.0.dist-info/top_level.txt
azure_utils-0.4.0.dist-info/RECORD
