Metadata-Version: 2.1
Name: azure_utils
Version: 0.4.0
Summary: Azure Utilities
Author-email: Connor Makowski <conmak@mit.edu>
Project-URL: Homepage, https://github.com/connor-makowski/azure_utils
Project-URL: Bug Tracker, https://github.com/connor-makowski/azure_utils/issues
Project-URL: Documentation, https://connor-makowski.github.io/azure_utils/azure_utils/blob_storage.html
Classifier: Programming Language :: Python :: 3
Classifier: License :: OSI Approved :: MIT License
Classifier: Operating System :: OS Independent
Requires-Python: >=3.6
License-File: LICENSE
Requires-Dist: azure-storage-blob ==12.19.0
